MnemoPwd-1.2.1.dist-info/DESCRIPTION.rst
MnemoPwd-1.2.1.dist-info/METADATA
MnemoPwd-1.2.1.dist-info/RECORD
MnemoPwd-1.2.1.dist-info/WHEEL
MnemoPwd-1.2.1.dist-info/entry_points.txt
MnemoPwd-1.2.1.dist-info/metadata.json
MnemoPwd-1.2.1.dist-info/top_level.txt
mnemopwd/__init__.py
mnemopwd/clientctl.py
mnemopwd/serverctl.py
mnemopwd/client/__init__.py
mnemopwd/client/corelayer/ClientCore.py
mnemopwd/client/corelayer/__init__.py
mnemopwd/client/corelayer/protocol/ProtocolHandler.py
mnemopwd/client/corelayer/protocol/StateS0.py
mnemopwd/client/corelayer/protocol/StateS1CA.py
mnemopwd/client/corelayer/protocol/StateS1CR.py
mnemopwd/client/corelayer/protocol/StateS1S.py
mnemopwd/client/corelayer/protocol/StateS21A.py
mnemopwd/client/corelayer/protocol/StateS21R.py
mnemopwd/client/corelayer/protocol/StateS22A.py
mnemopwd/client/corelayer/protocol/StateS22R.py
mnemopwd/client/corelayer/protocol/StateS31A.py
mnemopwd/client/corelayer/protocol/StateS31R.py
mnemopwd/client/corelayer/protocol/StateS32A.py
mnemopwd/client/corelayer/protocol/StateS32R.py
mnemopwd/client/corelayer/protocol/StateS33A.py
mnemopwd/client/corelayer/protocol/StateS33R.py
mnemopwd/client/corelayer/protocol/StateS34A.py
mnemopwd/client/corelayer/protocol/StateS34R.py
mnemopwd/client/corelayer/protocol/StateS35A.py
mnemopwd/client/corelayer/protocol/StateS35R.py
mnemopwd/client/corelayer/protocol/StateS36A.py
mnemopwd/client/corelayer/protocol/StateS36R.py
mnemopwd/client/corelayer/protocol/StateS37A.py
mnemopwd/client/corelayer/protocol/StateS37R.py
mnemopwd/client/corelayer/protocol/StateSCC.py
mnemopwd/client/corelayer/protocol/__init__.py
mnemopwd/client/uilayer/ClientUI.py
mnemopwd/client/uilayer/__init__.py
mnemopwd/client/uilayer/uiapplication/ApplicationMenu.py
mnemopwd/client/uilayer/uiapplication/CreateMenu.py
mnemopwd/client/uilayer/uiapplication/EditionWindow.py
mnemopwd/client/uilayer/uiapplication/ExportImportMenu.py
mnemopwd/client/uilayer/uiapplication/LoginWindow.py
mnemopwd/client/uilayer/uiapplication/MainWindow.py
mnemopwd/client/uilayer/uiapplication/SearchWindow.py
mnemopwd/client/uilayer/uiapplication/UnlockScreenWindow.py
mnemopwd/client/uilayer/uiapplication/UserAccountDeletionWindow.py
