Metadata-Version: 2.0
Name: MnemoPwd
Version: 1.2.1
Summary: A client-server application to store secret information
Home-page: https://github.com/thethythy/Mnemopwd
Author: Thierry Lemeunier
Author-email: thethythy@gmail.com
License: BSD
Keywords: secret storage,security,elliptic cryptography,openssl
Platform: UNKNOWN
Classifier: Development Status :: 4 - Beta
Classifier: Environment :: Console
Classifier: Environment :: Console :: Curses
Classifier: License :: OSI Approved :: BSD License
Classifier: Operating System :: MacOS :: MacOS X
Classifier: Operating System :: POSIX
Classifier: Operating System :: POSIX :: Linux
Classifier: Programming Language :: Python :: 3.4
Classifier: Programming Language :: Python :: 3.5
Classifier: Programming Language :: Python :: 3.6
Classifier: Topic :: Security
Classifier: Topic :: Security :: Cryptography
Classifier: Topic :: Utilities
